fastapi_sqlalchemy/__init__.py
fastapi_sqlalchemy/exceptions.py
fastapi_sqlalchemy/middleware.py
fastapi_sqlalchemy/py.typed
FTSQLALCHEMY-0.2.1.dist-info/LICENSE
FTSQLALCHEMY-0.2.1.dist-info/METADATA
FTSQLALCHEMY-0.2.1.dist-info/WHEEL
FTSQLALCHEMY-0.2.1.dist-info/top_level.txt
FTSQLALCHEMY-0.2.1.dist-info/RECORD
