Metadata-Version: 2.1
Name: FTSQLALCHEMY
Version: 0.2.1
Summary: Adds simple SQLAlchemy support to FastAPI
Home-page: https://github.com/airdrop11t/django_test/
Author: JackTest
Author-email: workspaceelojack@gmail.com
License: MIT
Project-URL: Code, https://github.com/mfreeborn/fastapi-sqlalchemy
Project-URL: Issue tracker, https://github.com/mfreeborn/fastapi-sqlalchemy/issues
Classifier: Development Status :: 4 - Beta
Classifier: Environment :: Web Environment
Classifier: Framework :: AsyncIO
Classifier: Intended Audience :: Developers
Classifier: License :: OSI Approved :: MIT License
Classifier: Operating System :: OS Independent
Classifier: Programming Language :: Python :: 3.6
Classifier: Programming Language :: Python :: 3.7
Classifier: Programming Language :: Python :: 3.8
Classifier: Programming Language :: Python :: 3 :: Only
Classifier: Programming Language :: Python :: Implementation :: CPython
Classifier: Topic :: Internet :: WWW/HTTP :: HTTP Servers
Classifier: Topic :: Internet :: WWW/HTTP :: Dynamic Content
Classifier: Topic :: Software Development :: Libraries :: Python Modules
Requires-Python: >=3.7
License-File: LICENSE
Requires-Dist: starlette >=0.12.9
Requires-Dist: SQLAlchemy >=1.2
